morphomeasure/__init__.py
morphomeasure/cli.py
morphomeasure/features.py
morphomeasure/lmwrapper.py
morphomeasure/__pycache__/__init__.cpython-310.pyc
morphomeasure/__pycache__/__init__.cpython-311.pyc
morphomeasure/__pycache__/cli.cpython-310.pyc
morphomeasure/__pycache__/cli.cpython-311.pyc
morphomeasure/__pycache__/features.cpython-310.pyc
morphomeasure/__pycache__/features.cpython-311.pyc
morphomeasure/__pycache__/lmwrapper.cpython-310.pyc
morphomeasure/__pycache__/lmwrapper.cpython-311.pyc
morphomeasure-0.1.1.dist-info/licenses/LICENSE
morphomeasure-0.1.1.dist-info/METADATA
morphomeasure-0.1.1.dist-info/WHEEL
morphomeasure-0.1.1.dist-info/entry_points.txt
morphomeasure-0.1.1.dist-info/top_level.txt
morphomeasure-0.1.1.dist-info/RECORD
