Metadata-Version: 2.4
Name: morphomeasure
Version: 0.1.1
Summary: Python package and CLI for L-Measure-based morphometric extraction
Home-page: https://github.com/Masood-Akram/MorphoMeasure
Author: Masood Akram
Author-email: masood.ahmed.akram@gmail.com
Classifier: Programming Language :: Python :: 3
Classifier: License :: OSI Approved :: MIT License
Requires-Python: >=3.8
License-File: LICENSE
Requires-Dist: pandas
Dynamic: author
Dynamic: author-email
Dynamic: classifier
Dynamic: description
Dynamic: description-content-type
Dynamic: home-page
Dynamic: license-file
Dynamic: requires-dist
Dynamic: requires-python
Dynamic: summary
